[
  {
    "name": "Aether",
    "region": "Other World",
    "imageUrl": "https://static.wikia.nocookie.net/gensin-impact/images/a/a4/Icon_Emoji_Paimon%27s_Paintings_42_Aether_1.png/"
  },
  {
    "name": "Lumine",
    "region": "Other World",
    "imageUrl": "https://static.wikia.nocookie.net/gensin-impact/images/7/7d/Icon_Emoji_Paimon%27s_Paintings_42_Lumine_1.png/"
  },
  {
    "name": "Paimon",
    "region": "Other World",
    "imageUrl": "https://static.wikia.nocookie.net/gensin-impact/images/0/04/Icon_Emoji_Teyvat_Times_Series_Paimon_12.png/"
  },
  {
    "name": "Venti",
    "region": "Mondstadt",
    "imageUrl": "https://static.wikia.nocookie.net/gensin-impact/images/5/53/Icon_Emoji_Paimon%27s_Paintings_43_Venti_1.png/"
  },
  {
    "name": "Zhongli",
    "region": "Liyue",
    "imageUrl": "https://static.wikia.nocookie.net/gensin-impact/images/4/48/Icon_Emoji_Paimon%27s_Paintings_12_Zhongli_1.png/"
  },
  {
    "name": "Raiden Ei",
    "shortname": "Ei",
    "region": "Inazuma",
    "imageUrl": "https://static.wikia.nocookie.net/gensin-impact/images/d/d6/Icon_Emoji_Paimon%27s_Paintings_13_Raiden_Shogun_2.png/"
  },
  {
    "name": "Nahida",
    "region": "Sumeru",
    "imageUrl": "https://static.wikia.nocookie.net/gensin-impact/images/0/07/Icon_Emoji_Paimon%27s_Paintings_23_Nahida_2.png/"
  },
  {
    "name": "Furina de Fontaine",
    "shortname": "Furina",
    "region": "Fontaine",
    "imageUrl": "https://static.wikia.nocookie.net/gensin-impact/images/9/9e/Icon_Emoji_Paimon%27s_Paintings_26_Furina_1.png/"
  },
  {
    "name": "Mavuika",
    "region": "Natlan",
    "imageUrl": "https://static.wikia.nocookie.net/gensin-impact/images/2/2b/Icon_Emoji_Paimon%27s_Paintings_38_Mavuika_2.png/"
  },
  {
    "name": "Columbina Hyposelenia",
    "shortname": "Columbina",
    "region": "Nod-Krai",
    "imageUrl": "https://static.wikia.nocookie.net/gensin-impact/images/f/f5/Icon_Emoji_Paimon%27s_Paintings_44_Columbina_1.png/"
  },
  {
    "name": "Mona Megistus",
    "shortname": "Mona",
    "region": "Mondstadt",
    "imageUrl": "https://static.wikia.nocookie.net/gensin-impact/images/1/17/Icon_Emoji_Paimon%27s_Paintings_20_Mona_1.png/"
  },
  {
    "name": "Xiao",
    "region": "Liyue",
    "imageUrl": "https://static.wikia.nocookie.net/gensin-impact/images/9/9c/Icon_Emoji_Paimon%27s_Paintings_15_Xiao_1.png/"
  },
  {
    "name": "Yae Miko",
    "region": "Inazuma",
    "imageUrl": "https://static.wikia.nocookie.net/gensin-impact/images/a/a6/Icon_Emoji_Paimon%27s_Paintings_13_Yae_Miko_1.png/"
  },
  {
    "name": "Alhaitham",
    "region": "Sumeru",
    "imageUrl": "https://static.wikia.nocookie.net/gensin-impact/images/f/f3/Icon_Emoji_Paimon%27s_Paintings_21_Alhaitham_1.png/"
  },
  {
    "name": "Neuvillette",
    "region": "Fontaine",
    "imageUrl": "https://static.wikia.nocookie.net/gensin-impact/images/6/68/Icon_Emoji_Paimon%27s_Paintings_27_Neuvillette_1.png/"
  },
  {
    "name": "Citlali",
    "region": "Natlan",
    "imageUrl": "https://static.wikia.nocookie.net/gensin-impact/images/5/54/Icon_Emoji_Paimon%27s_Paintings_36_Citlali_1.png/"
  },
  {
    "name": "Xilonen",
    "region": "Natlan",
    "imageUrl": "https://static.wikia.nocookie.net/gensin-impact/images/d/db/Icon_Emoji_Paimon%27s_Paintings_36_Xilonen_3.png/"
  },
  {
    "name": "Kaeya Alberich",
    "shortname": "Kaeya",
    "region": "Mondstadt",
    "imageUrl": "https://static.wikia.nocookie.net/gensin-impact/images/1/12/Icon_Emoji_Paimon%27s_Paintings_25_Kaeya_2.png/"
  },
  {
    "name": "HuTao",
    "region": "Liyue",
    "imageUrl": "https://static.wikia.nocookie.net/gensin-impact/images/9/93/Icon_Emoji_Paimon%27s_Paintings_05_Hu_Tao_1.png/"
  },
  {
    "name": "Ganyu",
    "region": "Liyue",
    "imageUrl": "https://static.wikia.nocookie.net/gensin-impact/images/2/28/Icon_Emoji_Paimon%27s_Paintings_30_Ganyu_1.png/"
  },
  {
    "name": "Shenhe",
    "region": "Liyue",
    "imageUrl": "https://static.wikia.nocookie.net/gensin-impact/images/c/c8/Icon_Emoji_Paimon%27s_Paintings_30_Shenhe_1.png/"
  },
  {
    "name": "Yip Gaming",
    "shortname": "Gaming",
    "region": "Liyue",
    "imageUrl": "https://static.wikia.nocookie.net/gensin-impact/images/4/48/Icon_Emoji_Paimon%27s_Paintings_30_Gaming_4.png/"
  },
  {
    "name": "Dori",
    "region": "Sumeru",
    "imageUrl": "https://static.wikia.nocookie.net/gensin-impact/images/2/2d/Icon_Emoji_Paimon%27s_Paintings_17_Dori_1.png/"
  },
  {
    "name": "Layla",
    "region": "Sumeru",
    "imageUrl": "https://static.wikia.nocookie.net/gensin-impact/images/5/5a/Icon_Emoji_Paimon%27s_Paintings_45_Layla_1.png/"
  },
  {
    "name": "Chasca",
    "region": "Natlan",
    "imageUrl": "https://static.wikia.nocookie.net/gensin-impact/images/6/6d/Icon_Emoji_Paimon%27s_Paintings_36_Chasca_1.png/"
  },
  {
    "name": "Kamisato Ayato",
    "shortname": "Ayato",
    "region": "Inazuma",
    "imageUrl": "https://static.wikia.nocookie.net/gensin-impact/images/a/a8/Icon_Emoji_Paimon%27s_Paintings_14_Kamisato_Ayato_2.png/"
  },
  {
    "name": "Kamisato Ayaka",
    "shortname": "Ayaka",
    "region": "Inazuma",
    "imageUrl": "https://static.wikia.nocookie.net/gensin-impact/images/c/c6/Icon_Emoji_Paimon%27s_Paintings_08_Kamisato_Ayaka_4.png/"
  },
  {
    "name": "Kaedehara Kazuha",
    "shortname": "Kazuha",
    "region": "Inazuma",
    "imageUrl": "https://static.wikia.nocookie.net/gensin-impact/images/a/a4/Icon_Emoji_Paimon%27s_Paintings_16_Kaedehara_Kazuha_2.png/"
  },
  {
    "name": "Eula Lawrence",
    "shortname": "Eula",
    "region": "Mondstadt",
    "imageUrl": "https://static.wikia.nocookie.net/gensin-impact/images/d/d7/Icon_Emoji_Paimon%27s_Paintings_06_Eula_1.png/"
  },
  {
    "name": "Sayu",
    "region": "Inazuma",
    "imageUrl": "https://static.wikia.nocookie.net/gensin-impact/images/d/d3/Icon_Emoji_Paimon%27s_Paintings_08_Sayu_1.png/"
  },
  {
    "name": "Skirk",
    "region": "Abyss",
    "imageUrl": "https://static.wikia.nocookie.net/gensin-impact/images/f/f7/Icon_Emoji_Paimon%27s_Paintings_42_Skirk_1.png/"
  },
  {
    "name": "Xiangling",
    "region": "Liyue",
    "imageUrl": "https://static.wikia.nocookie.net/gensin-impact/images/6/63/Icon_Emoji_Paimon%27s_Paintings_38_Xiangling_2.png/"
  },
  {
    "name": "Kyryll Chudomirovich Flins",
    "shortname": "Flins",
    "region": "Nod-Krai",
    "imageUrl": "https://static.wikia.nocookie.net/gensin-impact/images/4/44/Icon_Emoji_Paimon%27s_Paintings_43_Flins_1.png/"
  },
  {
    "name": "Lauma",
    "region": "Nod-Krai",
    "imageUrl": "https://static.wikia.nocookie.net/gensin-impact/images/5/5a/Icon_Emoji_Paimon%27s_Paintings_44_Lauma_4.png/"
  },
  {
    "name": "Kinich",
    "region": "Natlan",
    "imageUrl": "https://static.wikia.nocookie.net/gensin-impact/images/1/19/Icon_Emoji_Paimon%27s_Paintings_35_Kinich_3.png/"
  },
  {
    "name": "Varesa",
    "region": "Natlan",
    "imageUrl": "https://static.wikia.nocookie.net/gensin-impact/images/9/94/Icon_Emoji_Paimon%27s_Paintings_40_Varesa_1.png/"
  },
  {
    "name": "Keqing",
    "region": "Liyue",
    "imageUrl": "https://static.wikia.nocookie.net/gensin-impact/images/3/3e/Icon_Emoji_Paimon%27s_Paintings_30_Keqing_1.png/"
  },
  {
    "name": "Wriothesley",
    "region": "Fontaine",
    "imageUrl": "https://static.wikia.nocookie.net/gensin-impact/images/1/1b/Icon_Emoji_Paimon%27s_Paintings_27_Wriothesley_4.png/"
  },
  {
    "name": "Clorinde",
    "region": "Fontaine",
    "imageUrl": "https://static.wikia.nocookie.net/gensin-impact/images/3/3c/Icon_Emoji_Paimon%27s_Paintings_28_Clorinde_1.png/"
  },
  {
    "name": "Sucrose",
    "region": "Mondstadt",
    "imageUrl": "https://static.wikia.nocookie.net/gensin-impact/images/9/98/Icon_Emoji_Paimon%27s_Paintings_04_Sucrose_1.png/"
  },
  {
    "name": "Nilou",
    "region": "Sumeru",
    "imageUrl": "https://static.wikia.nocookie.net/gensin-impact/images/e/ea/Icon_Emoji_Paimon%27s_Paintings_18_Nilou_1.png/"
  },
  {
    "name": "Xinyan",
    "region": "Liyue",
    "imageUrl": "https://static.wikia.nocookie.net/gensin-impact/images/4/45/Icon_Emoji_Paimon%27s_Paintings_03_Xinyan_1.png/"
  },
  {
    "name": "Ororon",
    "region": "Natlan",
    "imageUrl": "https://static.wikia.nocookie.net/gensin-impact/images/4/4e/Icon_Emoji_Paimon%27s_Paintings_36_Ororon_1.png/"
  },
  {
    "name": "Xingqiu",
    "region": "Liyue",
    "imageUrl": "https://static.wikia.nocookie.net/gensin-impact/images/b/b0/Icon_Emoji_Paimon%27s_Paintings_14_Xingqiu_1.png/"
  },
  {
    "name": "Emilie",
    "region": "Fontaine",
    "imageUrl": "https://static.wikia.nocookie.net/gensin-impact/images/7/72/Icon_Emoji_Paimon%27s_Paintings_34_Emilie_2.png/"
  },
  {
    "name": "Albedo",
    "region": "Mondstadt",
    "imageUrl": "https://static.wikia.nocookie.net/gensin-impact/images/9/91/Icon_Emoji_Paimon%27s_Paintings_11_Albedo_1.png/"
  },
  {
    "name": "Razor",
    "region": "Mondstadt",
    "imageUrl": "https://static.wikia.nocookie.net/gensin-impact/images/4/4b/Icon_Emoji_Paimon%27s_Paintings_18_Razor_2.png/"
  },
  {
    "name": "Chongyun",
    "region": "Liyue",
    "imageUrl": "https://static.wikia.nocookie.net/gensin-impact/images/2/2b/Icon_Emoji_Paimon%27s_Paintings_20_Chongyun_1.png/"
  },
  {
    "name": "Ningguang",
    "region": "Liyue",
    "imageUrl": "https://static.wikia.nocookie.net/gensin-impact/images/f/ff/Icon_Emoji_Paimon%27s_Paintings_12_Ningguang_2.png/"
  },
  {
    "name": "Arlecchino",
    "region": "Snezhnaya",
    "imageUrl": "https://static.wikia.nocookie.net/gensin-impact/images/4/4e/Icon_Emoji_Paimon%27s_Paintings_32_Arlecchino_1.png/"
  },
  {
    "name": "Faruzan",
    "region": "Sumeru",
    "imageUrl": "https://static.wikia.nocookie.net/gensin-impact/images/2/26/Icon_Emoji_Paimon%27s_Paintings_36_Faruzan_1.png/"
  },
  {
    "name": "Chiori",
    "region": "Inazuma",
    "imageUrl": "https://static.wikia.nocookie.net/gensin-impact/images/e/e8/Icon_Emoji_Paimon%27s_Paintings_31_Chiori_1.png/"
  },
  {
    "name": "Navia Caspar",
    "shortname": "Navia",
    "region": "Fontaine",
    "imageUrl": "https://static.wikia.nocookie.net/gensin-impact/images/2/2c/Icon_Emoji_Paimon%27s_Paintings_29_Navia_2.png/"
  },
  {
    "name": "Mika Schmidt",
    "shortname": "Mika",
    "region": "Mondstadt",
    "imageUrl": "https://static.wikia.nocookie.net/gensin-impact/images/e/ed/Icon_Emoji_Paimon%27s_Paintings_43_Mika_1.png/"
  },
  {
    "name": "Aino",
    "region": "Nod-Krai",
    "imageUrl": "https://static.wikia.nocookie.net/gensin-impact/images/c/cb/Icon_Emoji_Paimon%27s_Paintings_43_Aino_1.png/"
  },
  {
    "name": "Amber",
    "region": "Mondstadt",
    "imageUrl": "https://static.wikia.nocookie.net/gensin-impact/images/d/d2/Icon_Emoji_Paimon%27s_Paintings_31_Amber_1.png/"
  },
  {
    "name": "Iansan",
    "region": "Natlan",
    "imageUrl": "https://static.wikia.nocookie.net/gensin-impact/images/5/5b/Paimon%27s_Paintings_35_Iansan_1.png/"
  },
  {
    "name": "Mualani",
    "region": "Natlan",
    "imageUrl": "https://static.wikia.nocookie.net/gensin-impact/images/c/c5/Icon_Emoji_Paimon%27s_Paintings_35_Mualani_1.png/"
  },
  {
    "name": "Yanfei",
    "region": "Liyue",
    "imageUrl": "https://static.wikia.nocookie.net/gensin-impact/images/5/56/Icon_Emoji_Paimon%27s_Paintings_06_Yanfei_1.png/"
  },
  {
    "name": "Klee",
    "region": "Mondstadt",
    "imageUrl": "https://static.wikia.nocookie.net/gensin-impact/images/1/1c/Icon_Emoji_Paimon%27s_Paintings_25_Klee_2.png/"
  },
  {
    "name": "Kuki Shinobu",
    "shortname": "Shinobu",
    "region": "Inazuma",
    "imageUrl": "https://static.wikia.nocookie.net/gensin-impact/images/9/9d/Icon_Emoji_Paimon%27s_Paintings_32_Kuki_Shinobu_1.png/"
  },
  {
    "name": "Shikanoin Heizou",
    "shortname": "Heizou",
    "region": "Inazuma",
    "imageUrl": "https://static.wikia.nocookie.net/gensin-impact/images/7/79/Icon_Emoji_Paimon%27s_Paintings_16_Shikanoin_Heizou_4.png/"
  },
  {
    "name": "Tartaglia",
    "region": "Snezhnaya",
    "imageUrl": "https://static.wikia.nocookie.net/gensin-impact/images/9/9a/Icon_Emoji_Paimon%27s_Paintings_26_Tartaglia_1.png/"
  },
  {
    "name": "Kujou Sara",
    "shortname": "Sara",
    "region": "Inazuma",
    "imageUrl": "https://static.wikia.nocookie.net/gensin-impact/images/6/6e/Icon_Emoji_Paimon%27s_Paintings_09_Kujou_Sara_1.png/"
  },
  {
    "name": "Kaveh",
    "region": "Sumeru",
    "imageUrl": "https://static.wikia.nocookie.net/gensin-impact/images/1/11/Icon_Emoji_Paimon%27s_Paintings_23_Kaveh_3.png/"
  },
  {
    "name": "Barbara Pegg",
    "shortname": "Barbara",
    "region": "Mondstadt",
    "imageUrl": "https://static.wikia.nocookie.net/gensin-impact/images/0/0d/Icon_Emoji_Paimon%27s_Paintings_07_Barbara_4.png/"
  },
  {
    "name": "Cyno",
    "region": "Sumeru",
    "imageUrl": "https://static.wikia.nocookie.net/gensin-impact/images/0/05/Icon_Emoji_Paimon%27s_Paintings_18_Cyno_3.png/"
  },
  {
    "name": "Yoimiya",
    "region": "Inazuma",
    "imageUrl": "https://static.wikia.nocookie.net/gensin-impact/images/6/69/Icon_Emoji_Paimon%27s_Paintings_16_Yoimiya_2.png/"
  },
  {
    "name": "Lisa Minci",
    "shortname": "Lisa",
    "region": "Mondstadt",
    "imageUrl": "https://static.wikia.nocookie.net/gensin-impact/images/d/d6/Icon_Emoji_Paimon%27s_Paintings_31_Lisa_1.png/"
  },
  {
    "name": "Escoffier",
    "region": "Fontaine",
    "imageUrl": "https://static.wikia.nocookie.net/gensin-impact/images/3/31/Icon_Emoji_Paimon%27s_Paintings_41_Escoffier_2.png/"
  },
  {
    "name": "Arataki Itto",
    "shortname": "Itto",
    "region": "Inazuma",
    "imageUrl": "https://static.wikia.nocookie.net/gensin-impact/images/b/bf/Icon_Emoji_Paimon%27s_Paintings_15_Arataki_Itto_2.png/"
  },
  {
    "name": "Sethos",
    "region": "Sumeru",
    "imageUrl": "https://static.wikia.nocookie.net/gensin-impact/images/e/e7/Icon_Emoji_Paimon%27s_Paintings_33_Sethos_3.png/"
  },
  {
    "name": "Fischl von Luftschloss Narfidort",
    "shortname": "Fischl",
    "region": "Mondstadt",
    "imageUrl": "https://static.wikia.nocookie.net/gensin-impact/images/b/b8/Icon_Emoji_Paimon%27s_Paintings_04_Fischl_2.png/"
  },
  {
    "name": "Yun Jin",
    "region": "Liyue",
    "imageUrl": "https://static.wikia.nocookie.net/gensin-impact/images/0/05/Icon_Emoji_Paimon%27s_Paintings_12_Yun_Jin_2.png/"
  },
  {
    "name": "Gorou",
    "region": "Inazuma",
    "imageUrl": "https://static.wikia.nocookie.net/gensin-impact/images/b/b3/Icon_Emoji_Paimon%27s_Paintings_11_Gorou_1.png/"
  },
  {
    "name": "Collei",
    "region": "Sumeru",
    "imageUrl": "https://static.wikia.nocookie.net/gensin-impact/images/4/4a/Icon_Emoji_Paimon%27s_Paintings_17_Collei_4.png/"
  },
  {
    "name": "Candace",
    "region": "Sumeru",
    "imageUrl": "https://static.wikia.nocookie.net/gensin-impact/images/3/31/Icon_Emoji_Paimon%27s_Paintings_18_Candace_1.png/"
  },
  {
    "name": "Diluc Ragnvindr",
    "shortname": "Diluc",
    "region": "Mondstadt",
    "imageUrl": "https://static.wikia.nocookie.net/gensin-impact/images/e/e7/Icon_Emoji_Paimon%27s_Paintings_31_Diluc_1.png/"
  },
  {
    "name": "Baizhu",
    "region": "Liyue",
    "imageUrl": "https://static.wikia.nocookie.net/gensin-impact/images/8/8b/Icon_Emoji_Paimon%27s_Paintings_23_Baizhu_3.png/"
  },
  {
    "name": "Kachina",
    "region": "Natlan",
    "imageUrl": "https://static.wikia.nocookie.net/gensin-impact/images/8/8f/Icon_Emoji_Paimon%27s_Paintings_40_Kachina_1.png/"
  },
  {
    "name": "Yelan",
    "region": "Liyue",
    "imageUrl": "https://static.wikia.nocookie.net/gensin-impact/images/3/37/Icon_Emoji_Paimon%27s_Paintings_21_Yelan_1.png/"
  },
  {
    "name": "Xianyun",
    "region": "Liyue",
    "imageUrl": "https://static.wikia.nocookie.net/gensin-impact/images/3/34/Icon_Emoji_Paimon%27s_Paintings_30_Xianyun_1.png/"
  },
  {
    "name": "Charlotte",
    "region": "Fontaine",
    "imageUrl": "https://static.wikia.nocookie.net/gensin-impact/images/4/4b/Icon_Emoji_Paimon%27s_Paintings_28_Charlotte_4.png/"
  },
  {
    "name": "Dehya",
    "region": "Sumeru",
    "imageUrl": "https://static.wikia.nocookie.net/gensin-impact/images/3/36/Icon_Emoji_Paimon%27s_Paintings_22_Dehya_3.png/"
  },
  {
    "name": "Sigewinne",
    "region": "Fontaine",
    "imageUrl": "https://static.wikia.nocookie.net/gensin-impact/images/a/a4/Icon_Emoji_Paimon%27s_Paintings_33_Sigewinne_1.png/"
  },
  {
    "name": "Noelle",
    "region": "Mondstadt",
    "imageUrl": "https://static.wikia.nocookie.net/gensin-impact/images/b/b5/Icon_Emoji_Paimon%27s_Paintings_27_Noelle_1.png/"
  },
  {
    "name": "Yumemizuki Mizuki",
    "shortname": "Mizuki",
    "region": "Inazuma",
    "imageUrl": "https://static.wikia.nocookie.net/gensin-impact/images/4/4b/Icon_Emoji_Paimon%27s_Paintings_39_Yumemizuki_Mizuki_3.png/"
  },
  {
    "name": "Jean Gunnhildr",
    "shortname": "Jean",
    "region": "Mondstadt",
    "imageUrl": "https://static.wikia.nocookie.net/gensin-impact/images/9/91/Icon_Emoji_Paimon%27s_Paintings_41_Jean_1.png/"
  },
  {
    "name": "Yaoyao",
    "region": "Liyue",
    "imageUrl": "https://static.wikia.nocookie.net/gensin-impact/images/0/01/Icon_Emoji_Paimon%27s_Paintings_21_Yaoyao_2.png/"
  },
  {
    "name": "Qiqi",
    "region": "Liyue",
    "imageUrl": "https://static.wikia.nocookie.net/gensin-impact/images/f/f8/Icon_Emoji_Paimon%27s_Paintings_02_Qiqi_1.png/"
  },
  {
    "name": "Bennett",
    "region": "Mondstadt",
    "imageUrl": "https://static.wikia.nocookie.net/gensin-impact/images/6/6f/Icon_Emoji_Paimon%27s_Paintings_20_Bennett_1.png/"
  },
  {
    "name": "Sangonomiya Kokomi",
    "shortname": "Kokomi",
    "region": "Inazuma",
    "imageUrl": "https://static.wikia.nocookie.net/gensin-impact/images/2/27/Icon_Emoji_Paimon%27s_Paintings_13_Sangonomiya_Kokomi_2.png/"
  },
  {
    "name": "Beidou",
    "region": "Liyue",
    "imageUrl": "https://static.wikia.nocookie.net/gensin-impact/images/e/e4/Icon_Emoji_Paimon%27s_Paintings_08_Beidou_1.png/"
  },
  {
    "name": "Lynette",
    "region": "Fontaine",
    "imageUrl": "https://static.wikia.nocookie.net/gensin-impact/images/a/a2/Icon_Emoji_Paimon%27s_Paintings_28_Lynette_1.png/"
  },
  {
    "name": "Lyney",
    "region": "Fontaine",
    "imageUrl": "https://static.wikia.nocookie.net/gensin-impact/images/3/3c/Icon_Emoji_Paimon%27s_Paintings_28_Lyney_1.png/"
  },
  {
    "name": "Freminet",
    "region": "Fontaine",
    "imageUrl": "https://static.wikia.nocookie.net/gensin-impact/images/f/f6/Icon_Emoji_Paimon%27s_Paintings_28_Freminet_1.png/"
  },
  {
    "name": "Rosaria",
    "region": "Mondstadt",
    "imageUrl": "https://static.wikia.nocookie.net/gensin-impact/images/1/19/Icon_Emoji_Paimon%27s_Paintings_06_Rosaria_1.png/"
  },
  {
    "name": "Kirara",
    "region": "Inazuma",
    "imageUrl": "https://static.wikia.nocookie.net/gensin-impact/images/b/be/Icon_Emoji_Paimon%27s_Paintings_24_Kirara_1.png/"
  },
  {
    "name": "Diona",
    "region": "Mondstadt",
    "imageUrl": "https://static.wikia.nocookie.net/gensin-impact/images/d/d8/Icon_Emoji_Paimon%27s_Paintings_31_Diona_1.png/"
  },
  {
    "name": "Chevreuse",
    "region": "Fontaine",
    "imageUrl": "https://static.wikia.nocookie.net/gensin-impact/images/8/84/Icon_Emoji_Paimon%27s_Paintings_31_Chevreuse_1.png/"
  },
  {
    "name": "Thoma",
    "region": "Inazuma",
    "imageUrl": "https://static.wikia.nocookie.net/gensin-impact/images/0/01/Icon_Emoji_Paimon%27s_Paintings_10_Thoma_2.png/"
  },
  {
    "name": "Scaramouche",
    "region": "Sumeru",
    "imageUrl": "https://static.wikia.nocookie.net/gensin-impact/images/f/f5/Icon_Emoji_Paimon%27s_Paintings_20_Wanderer_3.png/"
  },
  {
    "name": "Tighnari",
    "region": "Sumeru",
    "imageUrl": "https://static.wikia.nocookie.net/gensin-impact/images/5/5e/Icon_Emoji_Paimon%27s_Paintings_17_Tighnari_1.png/"
  },
  {
    "name": "Zibai",
    "region": "Liyue",
    "imageUrl": ""
  },
  {
    "name": "Illuga",
    "region": "Nod-Krai",
    "imageUrl": ""
  },
  {
    "name": "Durin",
    "region": "Mondstadt",
    "imageUrl": ""
  },
  {
    "name": "Ineffa",
    "region": "Nod-Krai",
    "imageUrl": "https://static.wikia.nocookie.net/gensin-impact/images/7/7a/Icon_Emoji_Paimon%27s_Paintings_43_Ineffa_2.png/"
  },
  {
    "name": "Nefer",
    "region": "Nod-Krai",
    "imageUrl": "https://static.wikia.nocookie.net/gensin-impact/images/8/87/Icon_Emoji_Paimon%27s_Paintings_43_Nefer_1.png/"
  },
  {
    "name": "Dahlia",
    "region": "Mondstadt",
    "imageUrl": "https://static.wikia.nocookie.net/gensin-impact/images/a/ab/Icon_Emoji_Paimon%27s_Paintings_42_Dahlia_1.png/"
  },
  {
    "name": "Ifa",
    "region": "Natlan",
    "imageUrl": "https://static.wikia.nocookie.net/gensin-impact/images/1/1d/Icon_Emoji_Paimon%27s_Paintings_40_Ifa_1.png/"
  },
  {
    "name": "Jahoda",
    "region": "Nod-Krai",
    "imageUrl": "https://static.wikia.nocookie.net/gensin-impact/images/4/4e/Icon_Emoji_Paimon%27s_Paintings_43_Jahoda_1.png/"
  },
  {
    "name": "Lan Yan",
    "region": "Liyue",
    "imageUrl": "https://static.wikia.nocookie.net/gensin-impact/images/a/a3/Icon_Emoji_Paimon%27s_Paintings_38_Lan_Yan_2.png/"
  },
  {
    "name": "Dainsleif",
    "region": "Khaenri'ah",
    "imageUrl": "https://static.wikia.nocookie.net/gensin-impact/images/3/31/Icon_Emoji_Paimon%27s_Paintings_33_Dainsleif_2.png/"
  },
  {
    "name": "Signora",
    "region": "Snezhnaya",
    "imageUrl": "https://pbs.twimg.com/media/Fs0DcMvWIAAjxuU?format=png&name=small"
  },
  {
    "name": "Capitano",
    "region": "Khaenri'ah",
    "imageUrl": "https://static.wikia.nocookie.net/gensin-impact/images/e/e0/Icon_Emoji_Paimon%27s_Paintings_36_Capitano_1.png/"
  },
  {
    "name": "Rerir",
    "region": "Khaenri'ah",
    "imageUrl": "https://static.wikia.nocookie.net/gensin-impact/images/f/fe/Icon_Emoji_Paimon%27s_Paintings_45_Rerir_1.png/"
  },
  {
    "name": "Varka",
    "region": "Mondstadt",
    "imageUrl": "https://static.wikia.nocookie.net/gensin-impact/images/4/45/Icon_Emoji_Paimon%27s_Paintings_45_Varka_1.png/"
  },
  {
    "name": "Sandrone",
    "region": "Snezhnaya",
    "imageUrl": "https://static.wikia.nocookie.net/gensin-impact/images/9/94/Icon_Emoji_Paimon%27s_Paintings_45_Sandrone_1.png/"
  }
]
